{
  "meta": {
    "source": "naver:api-gw",
    "naverGameId": "20260721HHHT02026",
    "fetchedAt": "2026-07-20T21:03:43+09:00"
  },
  "gameInfo": {
    "aFullName": "한화 이글스",
    "hPCode": "52641",
    "hCode": "HT",
    "hName": "KIA",
    "cancelFlag": "N",
    "gdate": 20260721,
    "aPCode": "56709",
    "round": 10,
    "gtime": "18:30",
    "aName": "한화",
    "gameFlag": "0",
    "hFullName": "KIA 타이거즈",
    "stadium": "광주",
    "aCode": "HH",
    "optionFlag": 1,
    "ptsFlag": "Y",
    "isPostSeason": false,
    "statusCode": "0"
  },
  "homeStandings": {
    "d": 2,
    "era": "4.24",
    "hra": "0.269",
    "w": 48,
    "wra": "0.545",
    "name": "KIA",
    "rank": 4,
    "hr": 105,
    "l": 40,
    "seriesOutcome": {
      "d": 2,
      "w": 48,
      "l": 40
    }
  },
  "awayStandings": {
    "d": 3,
    "era": "4.60",
    "hra": "0.273",
    "w": 40,
    "wra": "0.482",
    "name": "한화",
    "rank": 6,
    "hr": 100,
    "l": 43,
    "seriesOutcome": {
      "d": 3,
      "w": 40,
      "l": 43
    }
  },
  "seasonVsResult": {
    "ad": 0,
    "hl": 4,
    "aw": 4,
    "aCode": "HH",
    "al": 5,
    "hCode": "HT",
    "hd": 0,
    "hw": 5
  },
  "homeTeamPreviousGames": [
    {
      "gameId": "20260719HTSK02026",
      "result": "승",
      "hScore": 5,
      "aName": "KIA",
      "aScore": 9,
      "gyear": 2026,
      "gmkey": "20260719HTSK0",
      "gweek": "일",
      "aCode": "HT",
      "hCode": "SK",
      "hName": "SSG",
      "gdate": 20260719
    },
    {
      "gameId": "20260718HTSK02026",
      "result": "승",
      "hScore": 2,
      "aName": "KIA",
      "aScore": 12,
      "gyear": 2026,
      "gmkey": "20260718HTSK0",
      "gweek": "토",
      "aCode": "HT",
      "hCode": "SK",
      "hName": "SSG",
      "gdate": 20260718
    },
    {
      "gameId": "20260717HTSK02026",
      "result": "승",
      "hScore": 3,
      "aName": "KIA",
      "aScore": 6,
      "gyear": 2026,
      "gmkey": "20260717HTSK0",
      "gweek": "금",
      "aCode": "HT",
      "hCode": "SK",
      "hName": "SSG",
      "gdate": 20260717
    },
    {
      "gameId": "20260716HTSK02026",
      "result": "패",
      "hScore": 6,
      "aName": "KIA",
      "aScore": 0,
      "gyear": 2026,
      "gmkey": "20260716HTSK0",
      "gweek": "목",
      "aCode": "HT",
      "hCode": "SK",
      "hName": "SSG",
      "gdate": 20260716
    },
    {
      "gameId": "20260709HTLT02026",
      "result": "승",
      "hScore": 2,
      "aName": "KIA",
      "aScore": 5,
      "gyear": 2026,
      "gmkey": "20260709HTLT0",
      "gweek": "목",
      "aCode": "HT",
      "hCode": "LT",
      "hName": "롯데",
      "gdate": 20260709
    }
  ],
  "awayTeamPreviousGames": [
    {
      "gameId": "20260719WOHH02026",
      "result": "무",
      "hScore": 9,
      "aName": "키움",
      "aScore": 9,
      "gyear": 2026,
      "gmkey": "20260719WOHH0",
      "gweek": "일",
      "aCode": "WO",
      "hCode": "HH",
      "hName": "한화",
      "gdate": 20260719
    },
    {
      "gameId": "20260718WOHH02026",
      "result": "패",
      "hScore": 2,
      "aName": "키움",
      "aScore": 4,
      "gyear": 2026,
      "gmkey": "20260718WOHH0",
      "gweek": "토",
      "aCode": "WO",
      "hCode": "HH",
      "hName": "한화",
      "gdate": 20260718
    },
    {
      "gameId": "20260717WOHH02026",
      "result": "패",
      "hScore": 6,
      "aName": "키움",
      "aScore": 7,
      "gyear": 2026,
      "gmkey": "20260717WOHH0",
      "gweek": "금",
      "aCode": "WO",
      "hCode": "HH",
      "hName": "한화",
      "gdate": 20260717
    },
    {
      "gameId": "20260716WOHH02026",
      "result": "패",
      "hScore": 5,
      "aName": "키움",
      "aScore": 14,
      "gyear": 2026,
      "gmkey": "20260716WOHH0",
      "gweek": "목",
      "aCode": "WO",
      "hCode": "HH",
      "hName": "한화",
      "gdate": 20260716
    },
    {
      "gameId": "20260709NCHH02026",
      "result": "승",
      "hScore": 6,
      "aName": "NC",
      "aScore": 4,
      "gyear": 2026,
      "gmkey": "20260709NCHH0",
      "gweek": "목",
      "aCode": "NC",
      "hCode": "HH",
      "hName": "한화",
      "gdate": 20260709
    }
  ],
  "homeStarter": {
    "currentSeasonStatsOnOpponents": {
      "bb": 2,
      "kk": 8,
      "gameCount": 2,
      "s": 0,
      "era": "1.00",
      "w": 2,
      "inn": "9.0",
      "l": 0,
      "er": 1
    },
    "playerInfo": {
      "backnum": "41",
      "hitType": "우투우타",
      "pCode": "52641",
      "name": "황동하",
      "birth": "20020730",
      "weight": "96.0",
      "height": "183.0"
    },
    "currentPitKindStats": [
      {
        "pit_rt": 38.29999923706055,
        "type": "FAST",
        "speed": 141
      },
      {
        "pit_rt": 33.29999923706055,
        "type": "SLID",
        "speed": 129
      },
      {
        "pit_rt": 21.100000381469727,
        "type": "FORK",
        "speed": 130
      }
    ],
    "currentSeasonStats": {
      "teamName": "KIA",
      "bb": 27,
      "kk": 50,
      "gameCount": 18,
      "gday": "20260719",
      "inn": "68.0",
      "hp": 3,
      "teamCode": "HT",
      "hr": 12,
      "l": 3,
      "er": 33,
      "whip": "1.38",
      "hit": 67,
      "r": 38,
      "s": 0,
      "era": "4.37",
      "w": 6,
      "inn2": "68"
    }
  },
  "awayStarter": {
    "currentSeasonStatsOnOpponents": {
      "bb": "0",
      "kk": "0",
      "gameCount": "0",
      "s": "0",
      "era": "0.00",
      "w": "0",
      "inn": "0",
      "l": "0",
      "er": "0"
    },
    "playerInfo": {
      "backnum": "68",
      "hitType": "우투우타",
      "pCode": "56709",
      "name": "박준영",
      "birth": "20020603",
      "weight": "87.0",
      "height": "184.0"
    },
    "currentPitKindStats": [
      {
        "pit_rt": 49.70000076293945,
        "type": "FAST",
        "speed": 138
      },
      {
        "pit_rt": 24.600000381469727,
        "type": "SLID",
        "speed": 128
      },
      {
        "pit_rt": 16.100000381469727,
        "type": "CHUP",
        "speed": 121
      }
    ],
    "currentSeasonStats": {
      "teamName": "한화",
      "bb": 18,
      "kk": 31,
      "gameCount": 11,
      "gday": "20260719",
      "inn": "40.1",
      "hp": 6,
      "teamCode": "HH",
      "hr": 8,
      "l": 4,
      "er": 21,
      "whip": "1.26",
      "hit": 33,
      "r": 21,
      "s": 0,
      "era": "4.69",
      "w": 2,
      "inn2": "40 1/3"
    }
  }
}