{
  "meta": {
    "teamId": "lotte",
    "lineupDate": "2026-07-16",
    "lastUpdated": "2026-07-16T13:11:08+09:00",
    "gameId": "20260716LTSS02026",
    "kboGameId": "20260716LTSS0",
    "opponent": "삼성",
    "venue": "대구",
    "gameTime": "18:30",
    "lineupVerification": {
      "ours": {
        "source": "kbo-expected",
        "confirmed": false
      },
      "opponent": {
        "source": "kbo-opponent",
        "confirmed": false
      },
      "startingPitcher": {
        "source": "naver-preview"
      }
    }
  },
  "opponentMeta": {
    "teamShort": "삼성",
    "teamName": "삼성"
  },
  "batters": [
    {
      "order": 1,
      "name": "황성빈",
      "position": "중견수"
    },
    {
      "order": 2,
      "name": "고승민",
      "position": "1루수"
    },
    {
      "order": 3,
      "name": "레이예스",
      "position": "좌익수"
    },
    {
      "order": 4,
      "name": "한동희",
      "position": "지명타자"
    },
    {
      "order": 5,
      "name": "전민재",
      "position": "유격수"
    },
    {
      "order": 6,
      "name": "한태양",
      "position": "2루수"
    },
    {
      "order": 7,
      "name": "손호영",
      "position": "우익수"
    },
    {
      "order": 8,
      "name": "김세민",
      "position": "3루수"
    },
    {
      "order": 9,
      "name": "손성빈",
      "position": "포수"
    }
  ],
  "opponentBatters": [
    {
      "order": 1,
      "name": "김지찬",
      "position": "중견수"
    },
    {
      "order": 2,
      "name": "박승규",
      "position": "우익수"
    },
    {
      "order": 3,
      "name": "구자욱",
      "position": "좌익수"
    },
    {
      "order": 4,
      "name": "최형우",
      "position": "지명타자"
    },
    {
      "order": 5,
      "name": "디아즈",
      "position": "1루수"
    },
    {
      "order": 6,
      "name": "강민호",
      "position": "포수"
    },
    {
      "order": 7,
      "name": "김영웅",
      "position": "3루수"
    },
    {
      "order": 8,
      "name": "심재훈",
      "position": "유격수"
    },
    {
      "order": 9,
      "name": "양우현",
      "position": "2루수"
    }
  ],
  "startingPitcher": {
    "name": "로드리게스"
  },
  "opponentStartingPitcher": {
    "name": "양창섭"
  }
}