{
  "meta": {
    "naverGameId": "20260407SSHT02026",
    "gameDate": "2026-04-07",
    "lastUpdated": "2026-05-10T23:57:49+09:00"
  },
  "gameInfo": {
    "aFullName": "삼성 라이온즈",
    "hPCode": "77637",
    "hCode": "HT",
    "hName": "KIA",
    "cancelFlag": "N",
    "gdate": 20260407,
    "aPCode": "68415",
    "round": 1,
    "gtime": "18:30",
    "aName": "삼성",
    "gameFlag": "0",
    "hFullName": "KIA 타이거즈",
    "stadium": "광주",
    "aCode": "SS",
    "optionFlag": 1,
    "ptsFlag": "Y",
    "isPostSeason": false,
    "statusCode": "1"
  },
  "homeStandings": {
    "d": 0,
    "era": "5.00",
    "hra": "0.232",
    "w": 2,
    "wra": "0.250",
    "name": "KIA",
    "rank": 8,
    "hr": 5,
    "l": 6,
    "seriesOutcome": {
      "d": 0,
      "w": 2,
      "l": 6
    }
  },
  "awayStandings": {
    "d": 1,
    "era": "3.82",
    "hra": "0.247",
    "w": 4,
    "wra": "0.571",
    "name": "삼성",
    "rank": 4,
    "hr": 6,
    "l": 3,
    "seriesOutcome": {
      "d": 1,
      "w": 4,
      "l": 3
    }
  },
  "homeLineup": [
    {
      "order": 1,
      "name": "데일",
      "position": "유격수"
    },
    {
      "order": 2,
      "name": "김호령",
      "position": "중견수"
    },
    {
      "order": 3,
      "name": "김도영",
      "position": "3루수"
    },
    {
      "order": 4,
      "name": "카스트로",
      "position": "좌익수"
    },
    {
      "order": 5,
      "name": "나성범",
      "position": "지명타자"
    },
    {
      "order": 6,
      "name": "김선빈",
      "position": "2루수"
    },
    {
      "order": 7,
      "name": "박상준",
      "position": "1루수"
    },
    {
      "order": 8,
      "name": "김태군",
      "position": "포수"
    },
    {
      "order": 9,
      "name": "박재현",
      "position": "우익수"
    }
  ],
  "awayLineup": [
    {
      "order": 1,
      "name": "김지찬",
      "position": "중견수"
    },
    {
      "order": 2,
      "name": "류지혁",
      "position": "2루수"
    },
    {
      "order": 3,
      "name": "최형우",
      "position": "지명타자"
    },
    {
      "order": 4,
      "name": "디아즈",
      "position": "1루수"
    },
    {
      "order": 5,
      "name": "구자욱",
      "position": "좌익수"
    },
    {
      "order": 6,
      "name": "김영웅",
      "position": "3루수"
    },
    {
      "order": 7,
      "name": "강민호",
      "position": "포수"
    },
    {
      "order": 8,
      "name": "김헌곤",
      "position": "우익수"
    },
    {
      "order": 9,
      "name": "이재현",
      "position": "유격수"
    }
  ],
  "homeStarter": {
    "name": "양현종"
  },
  "awayStarter": {
    "name": "양창섭"
  },
  "scoreBoard": {
    "rheb": {
      "away": {
        "r": 10,
        "b": 4,
        "e": 0,
        "h": 11
      },
      "home": {
        "r": 3,
        "b": 8,
        "e": 0,
        "h": 6
      }
    },
    "inn": {
      "away": [
        1,
        0,
        0,
        0,
        0,
        0,
        0,
        5,
        4
      ],
      "home": [
        2,
        0,
        0,
        0,
        1,
        0,
        0,
        0,
        0
      ]
    }
  },
  "battersBoxscore": {
    "homeTotal": {
      "ab": 31,
      "hit": 6,
      "hra": "0.228",
      "rbi": 3,
      "run": 3,
      "sb": 3
    },
    "awayTotal": {
      "ab": 38,
      "hit": 11,
      "hra": "0.252",
      "rbi": 10,
      "run": 10,
      "sb": 0
    },
    "away": [
      {
        "bb": 0,
        "inn9": "3안",
        "batOrder": 1,
        "playerCode": "50458",
        "run": 1,
        "hr": 0,
        "sb": 0,
        "inn24": "",
        "inn23": "",
        "inn22": "",
        "hit": 1,
        "inn21": "",
        "pos": "중",
        "hra": "0.167",
        "inn25": "",
        "inn2": "",
        "inn1": "좌비",
        "inn4": "",
        "inn3": "삼진",
        "inn6": "유땅",
        "inn20": "",
        "inn5": "",
        "inn8": "중비",
        "inn7": "",
        "kk": 1,
        "ab": 5,
        "inn19": "",
        "inn18": "",
        "hasPlayerEnd": true,
        "inn13": "",
        "inn12": "",
        "inn11": "",
        "inn10": "",
        "inn17": "",
        "inn16": "",
        "inn15": "",
        "inn14": "",
        "name": "김지찬",
        "rbi": 0
      },
      {
        "bb": 1,
        "inn9": "우안",
        "batOrder": 2,
        "playerCode": "62234",
        "run": 3,
        "hr": 1,
        "sb": 0,
        "inn24": "",
        "inn23": "",
        "inn22": "",
        "hit": 3,
        "inn21": "",
        "pos": "二",
        "hra": "0.448",
        "inn25": "",
        "inn2": "",
        "inn1": "우홈",
        "inn4": "중비",
        "inn3": "",
        "inn6": "우2",
        "inn20": "",
        "inn5": "",
        "inn8": "4구",
        "inn7": "",
        "kk": 0,
        "ab": 4,
        "inn19": "",
        "inn18": "",
        "hasPlayerEnd": true,
        "inn13": "",
        "inn12": "",
        "inn11": "",
        "inn10": "",
        "inn17": "",
        "inn16": "",
        "inn15": "",
        "inn14": "",
        "name": "류지혁",
        "rbi": 2
      },
      {
        "bb": 2,
        "inn9": "중홈",
        "batOrder": 3,
        "playerCode": "72443",
        "run": 1,
        "hr": 1,
        "sb": 0,
        "inn24": "",
        "inn23": "",
        "inn22": "",
        "hit": 2,
        "inn21": "",
        "pos": "지",
        "hra": "0.324",
        "inn25": "",
        "inn2": "",
        "inn1": "투땅",
        "inn4": "4구",
        "inn3": "",
        "inn6": "4구",
        "inn20": "",
        "inn5": "",
        "inn8": "우2",
        "inn7": "",
        "kk": 0,
        "ab": 3,
        "inn19": "",
        "inn18": "",
        "hasPlayerEnd": true,
        "inn13": "",
        "inn12": "",
        "inn11": "",
        "inn10": "",
        "inn17": "",
        "inn16": "",
        "inn15": "",
        "inn14": "",
        "name": "최형우",
        "rbi": 4
      },
      {
        "bb": 0,
        "inn9": "우비",
        "batOrder": 4,
        "playerCode": "54400",
        "run": 1,
        "hr": 0,
        "sb": 0,
        "inn24": "",
        "inn23": "",
        "inn22": "",
        "hit": 1,
        "inn21": "",
        "pos": "一",
        "hra": "0.351",
        "inn25": "",
        "inn2": "",
        "inn1": "2땅",
        "inn4": "우비",
        "inn3": "",
        "inn6": "중비",
        "inn20": "",
        "inn5": "",
        "inn8": "우안",
        "inn7": "",
        "kk": 0,
        "ab": 5,
        "inn19": "",
        "inn18": "",
        "hasPlayerEnd": true,
        "inn13": "",
        "inn12": "",
        "inn11": "",
        "inn10": "",
        "inn17": "",
        "inn16": "",
        "inn15": "",
        "inn14": "",
        "name": "디아즈",
        "rbi": 1
      },
      {
        "bb": 0,
        "inn9": "중비",
        "batOrder": 5,
        "playerCode": "62404",
        "run": 1,
        "hr": 0,
        "sb": 0,
        "inn24": "",
        "inn23": "",
        "inn22": "",
        "hit": 0,
        "inn21": "",
        "pos": "좌",
        "hra": "0.229",
        "inn25": "",
        "inn2": "삼진",
        "inn1": "",
        "inn4": "2땅",
        "inn3": "",
        "inn6": "",
        "inn20": "",
        "inn5": "",
        "inn8": "유땅",
        "inn7": "좌비",
        "kk": 1,
        "ab": 5,
        "inn19": "",
        "inn18": "",
        "hasPlayerEnd": true,
        "inn13": "",
        "inn12": "",
        "inn11": "",
        "inn10": "",
        "inn17": "",
        "inn16": "",
        "inn15": "",
        "inn14": "",
        "name": "구자욱",
        "rbi": 0
      },
      {
        "bb": 0,
        "inn9": "",
        "batOrder": 5,
        "playerCode": "55440",
        "run": 0,
        "hr": 0,
        "sb": 0,
        "inn24": "",
        "inn23": "",
        "inn22": "",
        "hit": 0,
        "inn21": "",
        "pos": "좌",
        "hra": "0.111",
        "inn25": "",
        "inn2": "",
        "inn1": "",
        "inn4": "",
        "inn3": "",
        "inn6": "",
        "inn20": "",
        "inn5": "",
        "inn8": "",
        "inn7": "",
        "kk": 0,
        "ab": 0,
        "substituteIn": true,
        "inn19": "",
        "inn18": "",
        "hasPlayerEnd": true,
        "inn13": "",
        "inn12": "",
        "inn11": "",
        "inn10": "",
        "inn17": "",
        "inn16": "",
        "inn15": "",
        "inn14": "",
        "name": "함수호",
        "rbi": 0
      },
      {
        "bb": 1,
        "inn9": "",
        "batOrder": 6,
        "playerCode": "52430",
        "run": 1,
        "hr": 0,
        "sb": 0,
        "inn24": "",
        "inn23": "",
        "inn22": "",
        "hit": 1,
        "inn21": "",
        "pos": "三",
        "hra": "0.184",
        "inn25": "",
        "inn2": "삼진",
        "inn1": "",
        "inn4": "",
        "inn3": "",
        "inn6": "",
        "inn20": "",
        "inn5": "좌비",
        "inn8": "좌안",
        "inn7": "4구",
        "kk": 1,
        "ab": 3,
        "inn19": "",
        "inn18": "",
        "hasPlayerEnd": true,
        "inn13": "",
        "inn12": "",
        "inn11": "",
        "inn10": "",
        "inn17": "",
        "inn16": "",
        "inn15": "",
        "inn14": "",
        "name": "김영웅",
        "rbi": 1
      },
      {
        "bb": 0,
        "inn9": "중비",
        "batOrder": 6,
        "playerCode": "69416",
        "run": 0,
        "hr": 0,
        "sb": 0,
        "inn24": "",
        "inn23": "",
        "inn22": "",
        "hit": 0,
        "inn21": "",
        "pos": "유",
        "hra": "0.000",
        "inn25": "",
        "inn2": "",
        "inn1": "",
        "inn4": "",
        "inn3": "",
        "inn6": "",
        "inn20": "",
        "inn5": "",
        "inn8": "",
        "inn7": "",
        "kk": 0,
        "ab": 1,
        "substituteIn": true,
        "inn19": "",
        "inn18": "",
        "hasPlayerEnd": true,
        "inn13": "",
        "inn12": "",
        "inn11": "",
        "inn10": "",
        "inn17": "",
        "inn16": "",
        "inn15": "",
        "inn14": "",
        "name": "이해승",
        "rbi": 0
      },
      {
        "bb": 0,
        "inn9": "",
        "batOrder": 7,
        "playerCode": "74540",
        "run": 0,
        "hr": 0,
        "sb": 0,
        "inn24": "",
        "inn23": "",
        "inn22": "",
        "hit": 1,
        "inn21": "",
        "pos": "포",
        "hra": "0.167",
        "inn25": "",
        "inn2": "3땅",
        "inn1": "",
        "inn4": "",
        "inn3": "",
        "inn6": "",
        "inn20": "",
        "inn5": "포비",
        "inn8": "좌2",
        "inn7": "삼진",
        "kk": 1,
        "ab": 4,
        "inn19": "",
        "inn18": "",
        "hasPlayerEnd": true,
        "inn13": "",
        "inn12": "",
        "inn11": "",
        "inn10": "",
        "inn17": "",
        "inn16": "",
        "inn15": "",
        "inn14": "",
        "name": "강민호",
        "rbi": 2
      },
      {
        "bb": 0,
        "inn9": "",
        "batOrder": 8,
        "playerCode": "61404",
        "run": 0,
        "hr": 0,
        "sb": 0,
        "inn24": "",
        "inn23": "",
        "inn22": "",
        "hit": 0,
        "inn21": "",
        "pos": "우",
        "hra": "0.000",
        "inn25": "",
        "inn2": "",
        "inn1": "",
        "inn4": "",
        "inn3": "2비",
        "inn6": "",
        "inn20": "",
        "inn5": "좌비",
        "inn8": "",
        "inn7": "",
        "kk": 0,
        "ab": 2,
        "inn19": "",
        "inn18": "",
        "hasPlayerEnd": true,
        "inn13": "",
        "inn12": "",
        "inn11": "",
        "inn10": "",
        "inn17": "",
        "inn16": "",
        "inn15": "",
        "inn14": "",
        "name": "김헌곤",
        "rbi": 0
      },
      {
        "bb": 0,
        "inn9": "",
        "batOrder": 8,
        "playerCode": "65040",
        "run": 0,
        "hr": 0,
        "sb": 0,
        "inn24": "",
        "inn23": "",
        "inn22": "",
        "hit": 0,
        "inn21": "",
        "pos": "타우",
        "hra": "0.000",
        "inn25": "",
        "inn2": "",
        "inn1": "",
        "inn4": "",
        "inn3": "",
        "inn6": "",
        "inn20": "",
        "inn5": "",
        "inn8": "삼진",
        "inn7": "좌비",
        "kk": 1,
        "ab": 2,
        "substituteIn": true,
        "inn19": "",
        "inn18": "",
        "hasPlayerEnd": true,
        "inn13": "",
        "inn12": "",
        "inn11": "",
        "inn10": "",
        "inn17": "",
        "inn16": "",
        "inn15": "",
        "inn14": "",
        "name": "김태훈",
        "rbi": 0
      },
      {
        "bb": 0,
        "inn9": "",
        "batOrder": 9,
        "playerCode": "52415",
        "run": 0,
        "hr": 0,
        "sb": 0,
        "inn24": "",
        "inn23": "",
        "inn22": "",
        "hit": 0,
        "inn21": "",
        "pos": "유",
        "hra": "0.091",
        "inn25": "",
        "inn2": "",
        "inn1": "",
        "inn4": "",
        "inn3": "좌비",
        "inn6": "우비",
        "inn20": "",
        "inn5": "",
        "inn8": "",
        "inn7": "",
        "kk": 0,
        "ab": 2,
        "inn19": "",
        "inn18": "",
        "hasPlayerEnd": true,
        "inn13": "",
        "inn12": "",
        "inn11": "",
        "inn10": "",
        "inn17": "",
        "inn16": "",
        "inn15": "",
        "inn14": "",
        "name": "이재현",
        "rbi": 0
      },
      {
        "bb": 0,
        "inn9": "",
        "batOrder": 9,
        "playerCode": "69403",
        "run": 1,
        "hr": 0,
        "sb": 0,
        "inn24": "",
        "inn23": "",
        "inn22": "",
        "hit": 1,
        "inn21": "",
        "pos": "타",
        "hra": "0.750",
        "inn25": "",
        "inn2": "",
        "inn1": "",
        "inn4": "",
        "inn3": "",
        "inn6": "",
        "inn20": "",
        "inn5": "",
        "inn8": "좌2",
        "inn7": "",
        "kk": 0,
        "ab": 1,
        "substituteIn": true,
        "inn19": "",
        "inn18": "",
        "hasPlayerEnd": true,
        "inn13": "",
        "inn12": "",
        "inn11": "",
        "inn10": "",
        "inn17": "",
        "inn16": "",
        "inn15": "",
        "inn14": "",
        "name": "양우현",
        "rbi": 0
      },
      {
        "bb": 0,
        "inn9": "좌2",
        "batOrder": 9,
        "playerCode": "65586",
        "run": 1,
        "hr": 0,
        "sb": 0,
        "inn24": "",
        "inn23": "",
        "inn22": "",
        "hit": 1,
        "inn21": "",
        "pos": "三",
        "hra": "0.500",
        "inn25": "",
        "inn2": "",
        "inn1": "",
        "inn4": "",
        "inn3": "",
        "inn6": "",
        "inn20": "",
        "inn5": "",
        "inn8": "",
        "inn7": "",
        "kk": 0,
        "ab": 1,
        "substituteIn": true,
        "inn19": "",
        "inn18": "",
        "hasPlayerEnd": true,
        "inn13": "",
        "inn12": "",
        "inn11": "",
        "inn10": "",
        "inn17": "",
        "inn16": "",
        "inn15": "",
        "inn14": "",
        "name": "전병우",
        "rbi": 0
      }
    ],
    "home": [
      {
        "bb": 1,
        "inn9": "우비",
        "batOrder": 1,
        "playerCode": "56632",
        "run": 1,
        "hr": 0,
        "sb": 0,
        "inn24": "",
        "inn23": "",
        "inn22": "",
        "hit": 1,
        "inn21": "",
        "pos": "유",
        "hra": "0.321",
        "inn25": "",
        "inn2": "좌비",
        "inn1": "4구",
        "inn4": "",
        "inn3": "",
        "inn6": "",
        "inn20": "",
        "inn5": "삼진",
        "inn8": "",
        "inn7": "좌중2",
        "kk": 1,
        "ab": 4,
        "inn19": "",
        "inn18": "",
        "hasPlayerEnd": true,
        "inn13": "",
        "inn12": "",
        "inn11": "",
        "inn10": "",
        "inn17": "",
        "inn16": "",
        "inn15": "",
        "inn14": "",
        "name": "데일",
        "rbi": 0
      },
      {
        "bb": 0,
        "inn9": "사구",
        "batOrder": 2,
        "playerCode": "65653",
        "run": 0,
        "hr": 0,
        "sb": 1,
        "inn24": "",
        "inn23": "",
        "inn22": "",
        "hit": 2,
        "inn21": "",
        "pos": "중",
        "hra": "0.294",
        "inn25": "",
        "inn2": "",
        "inn1": "삼진",
        "inn4": "",
        "inn3": "중안",
        "inn6": "",
        "inn20": "",
        "inn5": "우2",
        "inn8": "",
        "inn7": "투희번",
        "kk": 1,
        "ab": 3,
        "inn19": "",
        "inn18": "",
        "hasPlayerEnd": true,
        "inn13": "",
        "inn12": "",
        "inn11": "",
        "inn10": "",
        "inn17": "",
        "inn16": "",
        "inn15": "",
        "inn14": "",
        "name": "김호령",
        "rbi": 1
      },
      {
        "bb": 0,
        "inn9": "",
        "batOrder": 2,
        "playerCode": "55926",
        "run": 0,
        "hr": 0,
        "sb": 0,
        "inn24": "",
        "inn23": "",
        "inn22": "",
        "hit": 0,
        "inn21": "",
        "pos": "주",
        "hra": "0.000",
        "inn25": "",
        "inn2": "",
        "inn1": "",
        "inn4": "",
        "inn3": "",
        "inn6": "",
        "inn20": "",
        "inn5": "",
        "inn8": "",
        "inn7": "",
        "kk": 0,
        "ab": 0,
        "substituteIn": true,
        "inn19": "",
        "inn18": "",
        "hasPlayerEnd": true,
        "inn13": "",
        "inn12": "",
        "inn11": "",
        "inn10": "",
        "inn17": "",
        "inn16": "",
        "inn15": "",
        "inn14": "",
        "name": "정현창",
        "rbi": 0
      },
      {
        "bb": 1,
        "inn9": "좌비",
        "batOrder": 3,
        "playerCode": "52605",
        "run": 1,
        "hr": 0,
        "sb": 1,
        "inn24": "",
        "inn23": "",
        "inn22": "",
        "hit": 1,
        "inn21": "",
        "pos": "三",
        "hra": "0.250",
        "inn25": "",
        "inn2": "",
        "inn1": "좌2",
        "inn4": "",
        "inn3": "삼진",
        "inn6": "",
        "inn20": "",
        "inn5": "3파",
        "inn8": "",
        "inn7": "고4",
        "kk": 1,
        "ab": 4,
        "inn19": "",
        "inn18": "",
        "hasPlayerEnd": true,
        "inn13": "",
        "inn12": "",
        "inn11": "",
        "inn10": "",
        "inn17": "",
        "inn16": "",
        "inn15": "",
        "inn14": "",
        "name": "김도영",
        "rbi": 0
      },
      {
        "bb": 0,
        "inn9": "2땅",
        "batOrder": 4,
        "playerCode": "56626",
        "run": 0,
        "hr": 0,
        "sb": 0,
        "inn24": "",
        "inn23": "",
        "inn22": "",
        "hit": 1,
        "inn21": "",
        "pos": "좌",
        "hra": "0.243",
        "inn25": "",
        "inn2": "",
        "inn1": "중안",
        "inn4": "",
        "inn3": "삼진",
        "inn6": "",
        "inn20": "",
        "inn5": "우비",
        "inn8": "",
        "inn7": "유비",
        "kk": 1,
        "ab": 5,
        "inn19": "",
        "inn18": "",
        "hasPlayerEnd": true,
        "inn13": "",
        "inn12": "",
        "inn11": "",
        "inn10": "",
        "inn17": "",
        "inn16": "",
        "inn15": "",
        "inn14": "",
        "name": "카스트로",
        "rbi": 2
      },
      {
        "bb": 0,
        "inn9": "",
        "batOrder": 5,
        "playerCode": "62947",
        "run": 0,
        "hr": 0,
        "sb": 0,
        "inn24": "",
        "inn23": "",
        "inn22": "",
        "hit": 0,
        "inn21": "",
        "pos": "지",
        "hra": "0.188",
        "inn25": "",
        "inn2": "",
        "inn1": "삼진",
        "inn4": "",
        "inn3": "1땅",
        "inn6": "삼진",
        "inn20": "",
        "inn5": "",
        "inn8": "",
        "inn7": "좌비",
        "kk": 2,
        "ab": 4,
        "inn19": "",
        "inn18": "",
        "hasPlayerEnd": true,
        "inn13": "",
        "inn12": "",
        "inn11": "",
        "inn10": "",
        "inn17": "",
        "inn16": "",
        "inn15": "",
        "inn14": "",
        "name": "나성범",
        "rbi": 0
      },
      {
        "bb": 3,
        "inn9": "",
        "batOrder": 6,
        "playerCode": "78603",
        "run": 0,
        "hr": 0,
        "sb": 0,
        "inn24": "",
        "inn23": "",
        "inn22": "",
        "hit": 0,
        "inn21": "",
        "pos": "二",
        "hra": "0.267",
        "inn25": "",
        "inn2": "",
        "inn1": "4구",
        "inn4": "유땅",
        "inn3": "",
        "inn6": "4구",
        "inn20": "",
        "inn5": "",
        "inn8": "4구",
        "inn7": "",
        "kk": 0,
        "ab": 1,
        "inn19": "",
        "inn18": "",
        "hasPlayerEnd": true,
        "inn13": "",
        "inn12": "",
        "inn11": "",
        "inn10": "",
        "inn17": "",
        "inn16": "",
        "inn15": "",
        "inn14": "",
        "name": "김선빈",
        "rbi": 0
      },
      {
        "bb": 2,
        "inn9": "",
        "batOrder": 7,
        "playerCode": "52634",
        "run": 0,
        "hr": 0,
        "sb": 0,
        "inn24": "",
        "inn23": "",
        "inn22": "",
        "hit": 0,
        "inn21": "",
        "pos": "一",
        "hra": "0.125",
        "inn25": "",
        "inn2": "",
        "inn1": "삼진",
        "inn4": "4구",
        "inn3": "",
        "inn6": "4구",
        "inn20": "",
        "inn5": "",
        "inn8": "",
        "inn7": "",
        "kk": 1,
        "ab": 1,
        "inn19": "",
        "inn18": "",
        "hasPlayerEnd": true,
        "inn13": "",
        "inn12": "",
        "inn11": "",
        "inn10": "",
        "inn17": "",
        "inn16": "",
        "inn15": "",
        "inn14": "",
        "name": "박상준",
        "rbi": 0
      },
      {
        "bb": 0,
        "inn9": "",
        "batOrder": 7,
        "playerCode": "66614",
        "run": 0,
        "hr": 0,
        "sb": 0,
        "inn24": "",
        "inn23": "",
        "inn22": "",
        "hit": 0,
        "inn21": "",
        "pos": "주一",
        "hra": "0.000",
        "inn25": "",
        "inn2": "",
        "inn1": "",
        "inn4": "",
        "inn3": "",
        "inn6": "",
        "inn20": "",
        "inn5": "",
        "inn8": "1땅",
        "inn7": "",
        "kk": 0,
        "ab": 1,
        "substituteIn": true,
        "inn19": "",
        "inn18": "",
        "hasPlayerEnd": true,
        "inn13": "",
        "inn12": "",
        "inn11": "",
        "inn10": "",
        "inn17": "",
        "inn16": "",
        "inn15": "",
        "inn14": "",
        "name": "김규성",
        "rbi": 0
      },
      {
        "bb": 0,
        "inn9": "",
        "batOrder": 8,
        "playerCode": "78122",
        "run": 0,
        "hr": 0,
        "sb": 0,
        "inn24": "",
        "inn23": "",
        "inn22": "",
        "hit": 0,
        "inn21": "",
        "pos": "포",
        "hra": "0.231",
        "inn25": "",
        "inn2": "3땅",
        "inn1": "",
        "inn4": "3병",
        "inn3": "",
        "inn6": "좌비",
        "inn20": "",
        "inn5": "",
        "inn8": "",
        "inn7": "",
        "kk": 0,
        "ab": 3,
        "inn19": "",
        "inn18": "",
        "hasPlayerEnd": true,
        "inn13": "",
        "inn12": "",
        "inn11": "",
        "inn10": "",
        "inn17": "",
        "inn16": "",
        "inn15": "",
        "inn14": "",
        "name": "김태군",
        "rbi": 0
      },
      {
        "bb": 0,
        "inn9": "",
        "batOrder": 8,
        "playerCode": "68646",
        "run": 0,
        "hr": 0,
        "sb": 0,
        "inn24": "",
        "inn23": "",
        "inn22": "",
        "hit": 0,
        "inn21": "",
        "pos": "포",
        "hra": "0.214",
        "inn25": "",
        "inn2": "",
        "inn1": "",
        "inn4": "",
        "inn3": "",
        "inn6": "",
        "inn20": "",
        "inn5": "",
        "inn8": "1땅",
        "inn7": "",
        "kk": 0,
        "ab": 1,
        "substituteIn": true,
        "inn19": "",
        "inn18": "",
        "hasPlayerEnd": true,
        "inn13": "",
        "inn12": "",
        "inn11": "",
        "inn10": "",
        "inn17": "",
        "inn16": "",
        "inn15": "",
        "inn14": "",
        "name": "한준수",
        "rbi": 0
      },
      {
        "bb": 0,
        "inn9": "",
        "batOrder": 9,
        "playerCode": "55636",
        "run": 1,
        "hr": 0,
        "sb": 1,
        "inn24": "",
        "inn23": "",
        "inn22": "",
        "hit": 1,
        "inn21": "",
        "pos": "우",
        "hra": "0.286",
        "inn25": "",
        "inn2": "1땅",
        "inn1": "",
        "inn4": "",
        "inn3": "",
        "inn6": "투땅",
        "inn20": "",
        "inn5": "중안",
        "inn8": "",
        "inn7": "",
        "kk": 0,
        "ab": 3,
        "inn19": "",
        "inn18": "",
        "hasPlayerEnd": true,
        "inn13": "",
        "inn12": "",
        "inn11": "",
        "inn10": "",
        "inn17": "",
        "inn16": "",
        "inn15": "",
        "inn14": "",
        "name": "박재현",
        "rbi": 0
      },
      {
        "bb": 0,
        "inn9": "",
        "batOrder": 9,
        "playerCode": "61353",
        "run": 0,
        "hr": 0,
        "sb": 0,
        "inn24": "",
        "inn23": "",
        "inn22": "",
        "hit": 0,
        "inn21": "",
        "pos": "타",
        "hra": "0.000",
        "inn25": "",
        "inn2": "",
        "inn1": "",
        "inn4": "",
        "inn3": "",
        "inn6": "",
        "inn20": "",
        "inn5": "",
        "inn8": "삼진",
        "inn7": "",
        "kk": 1,
        "ab": 1,
        "substituteIn": true,
        "inn19": "",
        "inn18": "",
        "hasPlayerEnd": true,
        "inn13": "",
        "inn12": "",
        "inn11": "",
        "inn10": "",
        "inn17": "",
        "inn16": "",
        "inn15": "",
        "inn14": "",
        "name": "고종욱",
        "rbi": 0
      },
      {
        "bb": 0,
        "inn9": "",
        "batOrder": 9,
        "playerCode": "67609",
        "run": 0,
        "hr": 0,
        "sb": 0,
        "inn24": "",
        "inn23": "",
        "inn22": "",
        "hit": 0,
        "inn21": "",
        "pos": "우",
        "hra": "0.333",
        "inn25": "",
        "inn2": "",
        "inn1": "",
        "inn4": "",
        "inn3": "",
        "inn6": "",
        "inn20": "",
        "inn5": "",
        "inn8": "",
        "inn7": "",
        "kk": 0,
        "ab": 0,
        "substituteIn": true,
        "inn19": "",
        "inn18": "",
        "hasPlayerEnd": true,
        "inn13": "",
        "inn12": "",
        "inn11": "",
        "inn10": "",
        "inn17": "",
        "inn16": "",
        "inn15": "",
        "inn14": "",
        "name": "박정우",
        "rbi": 0
      }
    ]
  },
  "pitchersBoxscore": {
    "away": [
      {
        "bb": 3,
        "kk": 6,
        "seasonLose": 0,
        "ab": 19,
        "gameCount": 2,
        "bf": 89,
        "seasonWin": 0,
        "pcode": "68415",
        "bbhp": 3,
        "inn": "5",
        "hr": 0,
        "l": 0,
        "er": 3,
        "hasPlayerEnd": true,
        "tb": "T",
        "pa": 22,
        "hit": 5,
        "r": 3,
        "s": 0,
        "era": "4.50",
        "w": 1,
        "name": "양창섭",
        "wls": ""
      },
      {
        "bb": 2,
        "kk": 1,
        "seasonLose": 0,
        "ab": 3,
        "gameCount": 5,
        "bf": 24,
        "seasonWin": 0,
        "pcode": "50464",
        "bbhp": 2,
        "inn": "1",
        "hr": 0,
        "l": 0,
        "er": 0,
        "hasPlayerEnd": true,
        "tb": "T",
        "pa": 5,
        "hit": 0,
        "r": 0,
        "s": 0,
        "era": "0.00",
        "w": 0,
        "name": "이승민",
        "wls": ""
      },
      {
        "bb": 1,
        "kk": 0,
        "seasonLose": 0,
        "ab": 1,
        "gameCount": 2,
        "bf": 3,
        "seasonWin": 0,
        "pcode": "56460",
        "bbhp": 1,
        "inn": "0 ⅓",
        "hr": 0,
        "l": 0,
        "er": 0,
        "hasPlayerEnd": true,
        "tb": "T",
        "pa": 3,
        "hit": 1,
        "r": 0,
        "s": 0,
        "era": "0.00",
        "w": 0,
        "name": "장찬희",
        "wls": ""
      },
      {
        "bb": 0,
        "kk": 0,
        "seasonLose": 0,
        "ab": 2,
        "gameCount": 5,
        "bf": 10,
        "seasonWin": 0,
        "pcode": "55455",
        "bbhp": 0,
        "inn": "0 ⅔",
        "hr": 0,
        "l": 0,
        "er": 0,
        "hasPlayerEnd": true,
        "tb": "T",
        "pa": 2,
        "hit": 0,
        "r": 0,
        "s": 0,
        "era": "6.00",
        "w": 1,
        "name": "배찬승",
        "wls": "승"
      },
      {
        "bb": 1,
        "kk": 1,
        "seasonLose": 0,
        "ab": 3,
        "gameCount": 4,
        "bf": 20,
        "seasonWin": 0,
        "pcode": "67421",
        "bbhp": 1,
        "inn": "1",
        "hr": 0,
        "l": 0,
        "er": 0,
        "hasPlayerEnd": true,
        "tb": "T",
        "pa": 4,
        "hit": 0,
        "r": 0,
        "s": 1,
        "era": "0.00",
        "w": 1,
        "name": "최지광",
        "wls": "홀"
      },
      {
        "bb": 0,
        "kk": 0,
        "seasonLose": 0,
        "ab": 3,
        "gameCount": 3,
        "bf": 12,
        "seasonWin": 0,
        "pcode": "62754",
        "bbhp": 1,
        "inn": "1",
        "hr": 0,
        "l": 0,
        "er": 0,
        "hasPlayerEnd": true,
        "tb": "T",
        "pa": 4,
        "hit": 0,
        "r": 0,
        "s": 0,
        "era": "6.75",
        "w": 0,
        "name": "임기영",
        "wls": ""
      }
    ],
    "home": [
      {
        "bb": 2,
        "kk": 3,
        "seasonLose": 0,
        "ab": 19,
        "gameCount": 2,
        "bf": 91,
        "seasonWin": 0,
        "pcode": "77637",
        "bbhp": 2,
        "inn": "5 ⅔",
        "hr": 1,
        "l": 1,
        "er": 1,
        "hasPlayerEnd": true,
        "tb": "B",
        "pa": 21,
        "hit": 2,
        "r": 1,
        "s": 0,
        "era": "3.72",
        "w": 0,
        "name": "양현종",
        "wls": ""
      },
      {
        "bb": 1,
        "kk": 0,
        "seasonLose": 0,
        "ab": 2,
        "gameCount": 5,
        "bf": 14,
        "seasonWin": 0,
        "pcode": "65769",
        "bbhp": 1,
        "inn": "0 ⅔",
        "hr": 0,
        "l": 0,
        "er": 0,
        "hasPlayerEnd": true,
        "tb": "B",
        "pa": 3,
        "hit": 0,
        "r": 0,
        "s": 0,
        "era": "7.71",
        "w": 0,
        "name": "김범수",
        "wls": "홀"
      },
      {
        "bb": 0,
        "kk": 1,
        "seasonLose": 0,
        "ab": 2,
        "gameCount": 4,
        "bf": 8,
        "seasonWin": 0,
        "pcode": "54610",
        "bbhp": 0,
        "inn": "0 ⅔",
        "hr": 0,
        "l": 0,
        "er": 0,
        "hasPlayerEnd": true,
        "tb": "B",
        "pa": 2,
        "hit": 0,
        "r": 0,
        "s": 0,
        "era": "0.00",
        "w": 0,
        "name": "성영탁",
        "wls": "홀"
      },
      {
        "bb": 1,
        "kk": 0,
        "seasonLose": 0,
        "ab": 6,
        "gameCount": 4,
        "bf": 28,
        "seasonWin": 0,
        "pcode": "66609",
        "bbhp": 1,
        "inn": "0 ⅔",
        "hr": 0,
        "l": 1,
        "er": 5,
        "hasPlayerEnd": true,
        "tb": "B",
        "pa": 7,
        "hit": 4,
        "r": 5,
        "s": 0,
        "era": "13.50",
        "w": 0,
        "name": "전상현",
        "wls": "패"
      },
      {
        "bb": 0,
        "kk": 1,
        "seasonLose": 0,
        "ab": 6,
        "gameCount": 5,
        "bf": 16,
        "seasonWin": 0,
        "pcode": "55267",
        "bbhp": 0,
        "inn": "0 ⅓",
        "hr": 1,
        "l": 0,
        "er": 4,
        "hasPlayerEnd": true,
        "tb": "B",
        "pa": 6,
        "hit": 5,
        "r": 4,
        "s": 0,
        "era": "13.50",
        "w": 0,
        "name": "홍민규",
        "wls": ""
      },
      {
        "bb": 0,
        "kk": 0,
        "seasonLose": 0,
        "ab": 3,
        "gameCount": 1,
        "bf": 10,
        "seasonWin": 0,
        "pcode": "51994",
        "bbhp": 0,
        "inn": "1",
        "hr": 0,
        "l": 0,
        "er": 0,
        "hasPlayerEnd": true,
        "tb": "B",
        "pa": 3,
        "hit": 0,
        "r": 0,
        "s": 0,
        "era": "0.00",
        "w": 0,
        "name": "한재승",
        "wls": ""
      }
    ]
  },
  "pitchingResult": [
    {
      "s": 0,
      "pCode": "54610",
      "w": 0,
      "name": "성영탁",
      "l": 0,
      "wls": "H"
    },
    {
      "s": 0,
      "pCode": "55455",
      "w": 1,
      "name": "배찬승",
      "l": 0,
      "wls": "W"
    },
    {
      "s": 0,
      "pCode": "65769",
      "w": 0,
      "name": "김범수",
      "l": 0,
      "wls": "H"
    },
    {
      "s": 0,
      "pCode": "66609",
      "w": 0,
      "name": "전상현",
      "l": 1,
      "wls": "L"
    },
    {
      "s": 1,
      "pCode": "67421",
      "w": 1,
      "name": "최지광",
      "l": 0,
      "wls": "H"
    }
  ],
  "etcRecords": [
    {
      "result": "김영웅(8회 2사 1,2루서 좌전 안타)",
      "how": "결승타"
    },
    {
      "result": "류지혁2호(1회1점 양현종) 최형우3호(9회3점 홍민규)",
      "how": "홈런"
    },
    {
      "result": "김도영(1회) 김호령(5회) 류지혁(6회) 데일(7회) 강민호(8회) 양우현(8회) 최형우(8회) 전병우(9회)",
      "how": "2루타"
    },
    {
      "result": "김호령(3회) 박재현(5회) 김도영(7회)",
      "how": "도루"
    },
    {
      "result": "최형우(8회)",
      "how": "주루사"
    },
    {
      "result": "김태군(4회)",
      "how": "병살타"
    },
    {
      "result": "강민호(3회)",
      "how": "포일"
    },
    {
      "result": "성영탁(7회) 홍민규(8회)",
      "how": "폭투"
    },
    {
      "result": "이기중 박종철 김태완 문동균",
      "how": "심판"
    }
  ]
}