{
  "meta": {
    "source": "naver:api-gw",
    "naverGameId": "20260619SSHH02026",
    "fetchedAt": "2026-06-19T16:41:35+09:00"
  },
  "gameInfo": {
    "aFullName": "삼성 라이온즈",
    "hPCode": "56709",
    "hCode": "HH",
    "hName": "한화",
    "cancelFlag": "N",
    "gdate": 20260619,
    "aPCode": "53375",
    "round": 7,
    "gtime": "18:30",
    "aName": "삼성",
    "gameFlag": "0",
    "hFullName": "한화 이글스",
    "stadium": "대전",
    "aCode": "SS",
    "optionFlag": 1,
    "ptsFlag": "Y",
    "isPostSeason": false,
    "statusCode": "0"
  },
  "homeStandings": {
    "d": 1,
    "era": "4.67",
    "hra": "0.274",
    "w": 32,
    "wra": "0.485",
    "name": "한화",
    "rank": 6,
    "hr": 73,
    "l": 34,
    "seriesOutcome": {
      "d": 1,
      "w": 32,
      "l": 34
    }
  },
  "awayStandings": {
    "d": 1,
    "era": "4.06",
    "hra": "0.273",
    "w": 39,
    "wra": "0.591",
    "name": "삼성",
    "rank": 3,
    "hr": 62,
    "l": 27,
    "seriesOutcome": {
      "d": 1,
      "w": 39,
      "l": 27
    }
  },
  "seasonVsResult": {
    "ad": 0,
    "hl": 5,
    "aw": 5,
    "aCode": "SS",
    "al": 1,
    "hCode": "HH",
    "hd": 0,
    "hw": 1
  },
  "homeTeamPreviousGames": [
    {
      "gameId": "20260618HHNC02026",
      "result": "패",
      "hScore": 6,
      "aName": "한화",
      "aScore": 0,
      "gyear": 2026,
      "gmkey": "20260618HHNC0",
      "gweek": "목",
      "aCode": "HH",
      "hCode": "NC",
      "hName": "NC",
      "gdate": 20260618
    },
    {
      "gameId": "20260617HHNC02026",
      "result": "패",
      "hScore": 5,
      "aName": "한화",
      "aScore": 4,
      "gyear": 2026,
      "gmkey": "20260617HHNC0",
      "gweek": "수",
      "aCode": "HH",
      "hCode": "NC",
      "hName": "NC",
      "gdate": 20260617
    },
    {
      "gameId": "20260616HHNC02026",
      "result": "패",
      "hScore": 6,
      "aName": "한화",
      "aScore": 5,
      "gyear": 2026,
      "gmkey": "20260616HHNC0",
      "gweek": "화",
      "aCode": "HH",
      "hCode": "NC",
      "hName": "NC",
      "gdate": 20260616
    },
    {
      "gameId": "20260614HHWO02026",
      "result": "패",
      "hScore": 3,
      "aName": "한화",
      "aScore": 2,
      "gyear": 2026,
      "gmkey": "20260614HHWO0",
      "gweek": "일",
      "aCode": "HH",
      "hCode": "WO",
      "hName": "키움",
      "gdate": 20260614
    },
    {
      "gameId": "20260613HHWO02026",
      "result": "패",
      "hScore": 3,
      "aName": "한화",
      "aScore": 1,
      "gyear": 2026,
      "gmkey": "20260613HHWO0",
      "gweek": "토",
      "aCode": "HH",
      "hCode": "WO",
      "hName": "키움",
      "gdate": 20260613
    }
  ],
  "awayTeamPreviousGames": [
    {
      "gameId": "20260618WOSS02026",
      "result": "승",
      "hScore": 4,
      "aName": "키움",
      "aScore": 3,
      "gyear": 2026,
      "gmkey": "20260618WOSS0",
      "gweek": "목",
      "aCode": "WO",
      "hCode": "SS",
      "hName": "삼성",
      "gdate": 20260618
    },
    {
      "gameId": "20260617WOSS02026",
      "result": "승",
      "hScore": 1,
      "aName": "키움",
      "aScore": 0,
      "gyear": 2026,
      "gmkey": "20260617WOSS0",
      "gweek": "수",
      "aCode": "WO",
      "hCode": "SS",
      "hName": "삼성",
      "gdate": 20260617
    },
    {
      "gameId": "20260616WOSS02026",
      "result": "승",
      "hScore": 4,
      "aName": "키움",
      "aScore": 1,
      "gyear": 2026,
      "gmkey": "20260616WOSS0",
      "gweek": "화",
      "aCode": "WO",
      "hCode": "SS",
      "hName": "삼성",
      "gdate": 20260616
    },
    {
      "gameId": "20260614SKSS02026",
      "result": "승",
      "hScore": 10,
      "aName": "SSG",
      "aScore": 8,
      "gyear": 2026,
      "gmkey": "20260614SKSS0",
      "gweek": "일",
      "aCode": "SK",
      "hCode": "SS",
      "hName": "삼성",
      "gdate": 20260614
    },
    {
      "gameId": "20260613SKSS02026",
      "result": "승",
      "hScore": 7,
      "aName": "SSG",
      "aScore": 6,
      "gyear": 2026,
      "gmkey": "20260613SKSS0",
      "gweek": "토",
      "aCode": "SK",
      "hCode": "SS",
      "hName": "삼성",
      "gdate": 20260613
    }
  ],
  "homeStarter": {
    "currentSeasonStatsOnOpponents": {
      "bb": "0",
      "kk": "0",
      "gameCount": "0",
      "s": "0",
      "era": "0.00",
      "w": "0",
      "inn": "0",
      "l": "0",
      "er": "0"
    },
    "playerInfo": {
      "backnum": "68",
      "hitType": "우투우타",
      "pCode": "56709",
      "name": "박준영",
      "birth": "20020603",
      "weight": "87.0",
      "height": "184.0"
    },
    "currentPitKindStats": [
      {
        "pit_rt": 50.29999923706055,
        "type": "FAST",
        "speed": 137
      },
      {
        "pit_rt": 22.200000762939453,
        "type": "SLID",
        "speed": 128
      },
      {
        "pit_rt": 13.899999618530273,
        "type": "CHUP",
        "speed": 121
      }
    ],
    "currentSeasonStats": {
      "teamName": "한화",
      "bb": 8,
      "kk": 18,
      "gameCount": 7,
      "gday": "20260618",
      "inn": "24.0",
      "hp": 3,
      "teamCode": "HH",
      "hr": 7,
      "l": 2,
      "er": 11,
      "whip": "1.21",
      "hit": 21,
      "r": 11,
      "s": 0,
      "era": "4.13",
      "w": 2,
      "inn2": "24"
    }
  },
  "awayStarter": {
    "currentSeasonStatsOnOpponents": {
      "bb": 2,
      "kk": 7,
      "gameCount": 2,
      "s": 0,
      "era": "2.77",
      "w": 1,
      "inn": "13.0",
      "l": 0,
      "er": 4
    },
    "playerInfo": {
      "backnum": "75",
      "hitType": "우투우타",
      "pCode": "53375",
      "name": "후라도",
      "birth": "19960130",
      "weight": "109.0",
      "height": "188.0"
    },
    "currentPitKindStats": [
      {
        "pit_rt": 28.200000762939453,
        "type": "TWOS",
        "speed": 142
      },
      {
        "pit_rt": 20.399999618530273,
        "type": "CHUP",
        "speed": 133
      },
      {
        "pit_rt": 16.899999618530273,
        "type": "FAST",
        "speed": 143
      }
    ],
    "currentSeasonStats": {
      "teamName": "삼성",
      "bb": 15,
      "kk": 55,
      "gameCount": 13,
      "gday": "20260618",
      "inn": "82.0",
      "hp": 3,
      "teamCode": "SS",
      "hr": 8,
      "l": 1,
      "er": 27,
      "whip": "1.23",
      "hit": 86,
      "r": 34,
      "s": 0,
      "era": "2.96",
      "w": 3,
      "inn2": "82"
    }
  }
}